btp_devops/__init__.py
btp_devops/config.py
btp_devops/pipeline.py
btp_devops/ssm_output.py
btp_devops/ssm_param_reader.py
btp_devops/utils.py
btp_devops-0.0.3.dist-info/METADATA
btp_devops-0.0.3.dist-info/WHEEL
btp_devops-0.0.3.dist-info/licenses/LICENSE
btp_devops-0.0.3.dist-info/RECORD
